[
    {
        "name": "不能经口进食",
        "score": "1"
    },
    {
        "name": "依赖管是进食,最少量的尝试进食食物或液体",
        "score": "2"
    },
    {
        "name": "依赖管饲进食,经口进食单一质地的食物或液体",
        "score": "3"
    },
    {
        "name": "完全经口进食单一质地的食物",
        "score": "4"
    },
    {
        "name": "完全经口进食多种质地的食物,但需要特殊的准备或代偿",
        "score": "5"
    },
    {
        "name": "完全经口进食，不需要特殊的准备,但有特殊的食物限制",
        "score": "6"
    },
    {
        "name": "完全经口进食没有限制",
        "score": "7"
    }
]